ardptt/__init__.py
ardptt/data_analyse.py
ardptt/data_tool.py
ardptt/generate_report.py
ardptt/performance_test.py
ardptt-1.0.3.dist-info/METADATA
ardptt-1.0.3.dist-info/WHEEL
ardptt-1.0.3.dist-info/top_level.txt
ardptt-1.0.3.dist-info/RECORD
