Metadata-Version: 2.1
Name: ardptt
Version: 1.0.3
Summary: android performance test tool
Home-page: https://github.com/wangzhilucien/ardptt
Author: gewanpiaoyi
Author-email: 745718548@qq.com
Requires-Dist: pyecharts (>=2.0.3)
